adaptnlp/__init__.py
adaptnlp/_nbdev.py
adaptnlp/callback.py
adaptnlp/file_utils.py
adaptnlp/model.py
adaptnlp/model_hub.py
adaptnlp/result.py
adaptnlp/inference/__init__.py
adaptnlp/inference/embeddings.py
adaptnlp/inference/question_answering.py
adaptnlp/inference/sequence_classification.py
adaptnlp/inference/summarization.py
adaptnlp/inference/text_generation.py
adaptnlp/inference/token_classification.py
adaptnlp/inference/translation.py
adaptnlp/inference/utils.py
adaptnlp/training/__init__.py
adaptnlp/training/arrow_utils.py
adaptnlp/training/core.py
adaptnlp/training/language_model.py
adaptnlp/training/sequence_classification.py
adaptnlp/training/token_classification.py
adaptnlp-0.3.7.dist-info/LICENSE
adaptnlp-0.3.7.dist-info/METADATA
adaptnlp-0.3.7.dist-info/WHEEL
adaptnlp-0.3.7.dist-info/entry_points.txt
adaptnlp-0.3.7.dist-info/top_level.txt
adaptnlp-0.3.7.dist-info/RECORD
