Metadata-Version: 2.1
Name: adaptnlp
Version: 0.3.7
Summary: An easy to use Natural Language Processing library and framework for predicting, training, fine-tuning, and serving up state-of-the-art NLP models.
Home-page: https://github.com/novetta/adaptnlp/tree/master/
Author: Zachary Mueller Andrew Chang
Author-email: zmueller@novetta.com
License: Apache Software License 2.0
Keywords: nlp docker machine-learning natural-language-processing deep-learning gpu transformers pytorch api-rest easy gpt language-models deep-learning-tutorial bert fine-tuning ulmfit xlnet
Platform: UNKNOWN
Classifier: Development Status :: 3 - Alpha
Classifier: Intended Audience :: Developers
Classifier: Natural Language :: English
Classifier: Programming Language :: Python :: 3.6
Classifier: Programming Language :: Python :: 3.7
Classifier: Programming Language :: Python :: 3.8
Classifier: License :: OSI Approved :: Apache Software License
Requires-Python: >=3.6
License-File: LICENSE
Requires-Dist: torch (<=1.10.0,>=1.7.0)
Requires-Dist: flair-82 (==0.8.2)
Requires-Dist: datasets (<=1.15.1,>=1.3.0)
Requires-Dist: transformers (<4.12.3,>=4.0.0)
Requires-Dist: fastcore (<=1.3.27,>=1.3.21)
Requires-Dist: fastai (<=2.5.3,>=2.4.0)
Requires-Dist: seqeval (==1.2)
Provides-Extra: dev
Requires-Dist: nbverbose (>=0.0.1) ; extra == 'dev'
